creeper_adventure/__about__.py
creeper_adventure/__init__.py
creeper_adventure/__main__.py
creeper_adventure/creeper.py
creeper_adventure/game.py
creeper_adventure/joytest.py
creeper_adventure/assets/chest.png
creeper_adventure/assets/crafting-table.png
creeper_adventure/assets/grass.png
creeper_adventure/assets/leaf.png
creeper_adventure/assets/log.png
creeper_adventure/assets/plank-bottom.png
creeper_adventure/assets/plank-top.png
creeper_adventure/assets/spotlight.png
creeper_adventure/assets/bee/idle/1.png
creeper_adventure/assets/creeper/idle/1.png
creeper_adventure/assets/creeper/idle/2.png
creeper_adventure/assets/creeper/idle/3.png
creeper_adventure/assets/creeper/idle/4.png
creeper_adventure/assets/creeper/idle/5.png
creeper_adventure/assets/oak_trees/1.png
creeper_adventure/assets/oak_trees/2.png
creeper_adventure/assets/oak_trees/4.png
creeper_adventure/assets/oak_trees/5.png
creeper_adventure/assets/oak_trees/6.png
creeper_adventure/assets/sounds/axe.mp3
creeper_adventure/assets/sounds/short-axe.mp3
creeper_adventure/assets/sounds/walking.mp3
creeper_adventure/assets/stev/idle/0.png
creeper_adventure/assets/stev/idle/1.png
creeper_adventure/cli/__init__.py
creeper_adventure-11.0.0.dist-info/METADATA
creeper_adventure-11.0.0.dist-info/WHEEL
creeper_adventure-11.0.0.dist-info/entry_points.txt
creeper_adventure-11.0.0.dist-info/licenses/LICENSE.txt
creeper_adventure-11.0.0.dist-info/RECORD
