Metadata-Version: 2.1
Name: creeper-adventure
Version: 11.0.0
Summary: a top down 2d adventure game
Project-URL: Documentation, https://github.com/unknown/creeper-adventure#readme
Project-URL: Issues, https://github.com/unknown/creeper-adventure/issues
Project-URL: Source, https://github.com/unknown/creeper-adventure
Author-email: "Waylon S. Walker" <waylon@waylonwalker.com>
License-Expression: MIT
License-File: LICENSE.txt
Classifier: Development Status :: 4 - Beta
Classifier: Programming Language :: Python
Classifier: Programming Language :: Python :: 3.7
Classifier: Programming Language :: Python :: 3.8
Classifier: Programming Language :: Python :: 3.9
Classifier: Programming Language :: Python :: 3.10
Classifier: Programming Language :: Python :: 3.11
Classifier: Programming Language :: Python :: Implementation :: CPython
Classifier: Programming Language :: Python :: Implementation :: PyPy
Requires-Python: >=3.7
Requires-Dist: click
Requires-Dist: more-itertools
Requires-Dist: pygame
